Workbook

Sheet Hymnes
A1: Continent | B1: Drapeau | C1: Pays / territoire | D1: Statut | E1: Hymne (titre original) | F1: Titre en français | G1: Parolier(s) | H1: Compositeur(s) | I1: Date des paroles | J1: Date de la musique | K1: Date d'adoption | L1: Paroles originales | M1: Paroles translittérées | N1: Traduction française | O1: Paroles reproduites | P1: Source des paroles | Q1: Lien audio (Wikimedia Commons) | R1: Remarques | S1: Fichier audio direct (URL .mp3 / .ogg) | T1: Code ISO
A2: Afrique | B2: 🇿🇦 | C2: Afrique du Sud | D2: État souverain | E2: National Anthem of South Africa | F2: Hymne national d'Afrique du Sud | G2: Enoch Sontonga, C. J. Langenhoven (adaptation 1997) | H2: Enoch Sontonga, Marthinus Lourens de Villiers | I2: 1897 / 1918 / 1997 | J2: 1897 / 1921 | K2: 1997 | L2: Non reproduites ici : version officielle révisée après 1929 ou texte non vérifié — voir la source. | O2: Non | P2: https://fr.wikipedia.org/w/index.php?search=National+Anthem+of+South+Africa&title=Sp%C3%A9cial%3ARecherche&go=Go | Q2: https://commons.wikimedia.org/w/index.php?search=South+Africa+national+anthem&title=Special%3AMediaSearch&type=audio | R2: Hymne composite en 5 langues (xhosa, zoulou, sesotho, afrikaans, anglais) | T2: ZA
A3: Afrique | B3: 🇩🇿 | C3: Algérie | D3: État souverain | E3: قسماً (Qassaman) | F3: Nous jurons | G3: Moufdi Zakaria | H3: Mohamed Fawzi | I3: 1955 | J3: 1956 | K3: 1962 | L3: Non reproduites ici : texte postérieur à 1929, potentiellement protégé — voir la source. | O3: Non | P3: https://fr.wikipedia.org/w/index.php?search=Qassaman&title=Sp%C3%A9cial%3ARecherche&go=Go | Q3: https://commons.wikimedia.org/w/index.php?search=Algeria+national+anthem&title=Special%3AMediaSearch&type=audio | T3: DZ
A4: Afrique | B4: 🇦🇴 | C4: Angola | D4: État souverain | E4: Angola Avante! | F4: En avant, Angola ! | G4: Manuel Rui Alves Monteiro | H4: Rui Alberto Vieira Dias Mingas | I4: 1975 | J4: 1975 | K4: 1975 | L4: Non reproduites ici : texte postérieur à 1929, potentiellement protégé — voir la source. | O4: Non | P4: https://fr.wikipedia.org/w/index.php?search=Angola+Avante%21&title=Sp%C3%A9cial%3ARecherche&go=Go | Q4: https://commons.wikimedia.org/w/index.php?search=Angola+national+anthem&title=Special%3AMediaSearch&type=audio | T4: AO
A5: Afrique | B5: 🇧🇯 | C5: Bénin | D5: État souverain | E5: L'Aube nouvelle | F5: L'Aube nouvelle | G5: Gilbert Jean Dagnon | H5: Gilbert Jean Dagnon | I5: 1960 | J5: 1960 | K5: 1960 | L5: Non reproduites ici : texte postérieur à 1929, potentiellement protégé — voir la source. | O5: Non | P5: https://fr.wikipedia.org/w/index.php?search=L%27Aube+nouvelle&title=Sp%C3%A9cial%3ARecherche&go=Go | Q5: https://commons.wikimedia.org/w/index.php?search=Benin+national+anthem&title=Special%3AMediaSearch&type=audio | T5: BJ
A6: Afrique | B6: 🇧🇼 | C6: Botswana | D6: État souverain | E6: Fatshe leno la rona | F6: Béni soit ce noble pays | G6: Kgalemang Tumediso Motsete | H6: Kgalemang Tumediso Motsete | I6: 1962 | J6: 1962 | K6: 1966 | L6: Non reproduites ici : texte postérieur à 1929, potentiellement protégé — voir la source. | O6: Non | P6: https://fr.wikipedia.org/w/index.php?search=Fatshe+leno+la+rona&title=Sp%C3%A9cial%3ARecherche&go=Go | Q6: https://commons.wikimedia.org/w/index.php?search=Botswana+national+anthem&title=Special%3AMediaSearch&type=audio | T6: BW
A7: Afrique | B7: 🇧🇫 | C7: Burkina Faso | D7: État souverain | E7: Ditanyè | F7: Hymne de la victoire | G7: attribué à Thomas Sankara | H7: attribué à Thomas Sankara | I7: 1984 | J7: 1984 | K7: 1984 | L7: Non reproduites ici : texte postérieur à 1929, potentiellement protégé — voir la source. | O7: Non | P7: https://fr.wikipedia.org/w/index.php?search=Ditany%C3%A8&title=Sp%C3%A9cial%3ARecherche&go=Go | Q7: https://commons.wikimedia.org/w/index.php?search=Burkina+Faso+national+anthem&title=Special%3AMediaSearch&type=audio | T7: BF
A8: Afrique | B8: 🇧🇮 | C8: Burundi | D8: État souverain | E8: Burundi Bwacu | F8: Notre Burundi | G8: Jean-Baptiste Ntahokaja (collectif) | H8: Marc Barengayabo | I8: 1962 | J8: 1962 | K8: 1962 | L8: Non reproduites ici : texte postérieur à 1929, potentiellement protégé — voir la source. | O8: Non | P8: https://fr.wikipedia.org/w/index.php?search=Burundi+Bwacu&title=Sp%C3%A9cial%3ARecherche&go=Go | Q8: https://commons.wikimedia.org/w/index.php?search=Burundi+national+anthem&title=Special%3AMediaSearch&type=audio | T8: BI
A9: Afrique | B9: 🇨🇲 | C9: Cameroun | D9: État souverain | E9: Chant de ralliement | F9: Chant de ralliement | G9: René Djam Afame, Samuel Minkio Bamba, Moïse Nyatte Nko'o | H9: René Djam Afame | I9: 1928 (révisé 1970) | J9: 1928 | K9: 1957 (texte révisé 1970) | L9: Non reproduites ici : version officielle révisée après 1929 ou texte non vérifié — voir la source. | O9: Non | P9: https://fr.wikipedia.org/w/index.php?search=Chant+de+ralliement&title=Sp%C3%A9cial%3ARecherche&go=Go | Q9: https://commons.wikimedia.org/w/index.php?search=Cameroon+national+anthem&title=Special%3AMediaSearch&type=audio | R9: Texte officiel actuel : version révisée de 1970 | T9: CM
A10: Afrique | B10: 🇰🇲 | C10: Comores | D10: État souverain | E10: Udzima wa ya Masiwa | F10: L'Union des îles | G10: Said Hachim Sidi Abderemane | H10: Said Hachim Sidi Abderemane, Kamildine Abdallah | I10: 1978 | J10: 1978 | K10: 1978 | L10: Non reproduites ici : texte postérieur à 1929, potentiellement protégé — voir la source. | O10: Non | P10: https://fr.wikipedia.org/w/index.php?search=Udzima+wa+ya+Masiwa&title=Sp%C3%A9cial%3ARecherche&go=Go | Q10: https://commons.wikimedia.org/w/index.php?search=Comoros+national+anthem&title=Special%3AMediaSearch&type=audio | T10: KM
A11: Afrique | B11: 🇨🇬 | C11: Congo | D11: État souverain | E11: La Congolaise | F11: La Congolaise | G11: Jacques Tondra, Georges Kibanghi | H11: Jean Royer, Joseph Spadilière | I11: 1959 | J11: 1959 | K11: 1959 (rétabli 1991) | L11: Non reproduites ici : texte postérieur à 1929, potentiellement protégé — voir la source. | O11: Non | P11: https://fr.wikipedia.org/w/index.php?search=La+Congolaise&title=Sp%C3%A9cial%3ARecherche&go=Go | Q11: https://commons.wikimedia.org/w/index.php?search=Congo+national+anthem&title=Special%3AMediaSearch&type=audio | T11: CG
A12: Afrique | B12: 🇨🇩 | C12: Congo (Rép. dém.) | D12: État souverain | E12: Debout Congolais | F12: Debout, Congolais | G12: Joseph Lutumba | H12: Simon-Pierre Boka di Mpasi Londi | I12: 1960 | J12: 1960 | K12: 1960 (rétabli 1997) | L12: Non reproduites ici : texte postérieur à 1929, potentiellement protégé — voir la source. | O12: Non | P12: https://fr.wikipedia.org/w/index.php?search=Debout+Congolais&title=Sp%C3%A9cial%3ARecherche&go=Go | Q12: https://commons.wikimedia.org/w/index.php?search=DR+Congo+national+anthem&title=Special%3AMediaSearch&type=audio | T12: CD
A13: Afrique | B13: 🇨🇮 | C13: Côte d'Ivoire | D13: État souverain | E13: L'Abidjanaise | F13: L'Abidjanaise | G13: Mathieu Ekra, Joachim Bony, Pierre Marie Coty | H13: Pierre-Michel Pango | I13: 1960 | J13: 1960 | K13: 1960 | L13: Non reproduites ici : texte postérieur à 1929, potentiellement protégé — voir la source. | O13: Non | P13: https://fr.wikipedia.org/w/index.php?search=L%27Abidjanaise&title=Sp%C3%A9cial%3ARecherche&go=Go | Q13: https://commons.wikimedia.org/w/index.php?search=Ivory+Coast+national+anthem&title=Special%3AMediaSearch&type=audio | T13: CI
A14: Afrique | B14: 🇩🇯 | C14: Djibouti | D14: État souverain | E14: Jabuuti | F14: Djibouti | G14: Aden Elmi | H14: Abdi Robleh | I14: 1977 | J14: 1977 | K14: 1977 | L14: Non reproduites ici : texte postérieur à 1929, potentiellement protégé — voir la source. | O14: Non | P14: https://fr.wikipedia.org/w/index.php?search=Jabuuti&title=Sp%C3%A9cial%3ARecherche&go=Go | Q14: https://commons.wikimedia.org/w/index.php?search=Djibouti+national+anthem&title=Special%3AMediaSearch&type=audio | T14: DJ
A15: Afrique | B15: 🇪🇬 | C15: Égypte | D15: État souverain | E15: بلادي بلادي بلادي (Bilady, Bilady, Bilady) | F15: Ma patrie, ma patrie, ma patrie | G15: Mohamed Younis al-Qadi | H15: Sayed Darwish | I15: 1923 | J15: 1923 | K15: 1979 | L15: (Refrain) بلادي بلادي بلادي لكِ حبي وفؤادي بلادي بلادي بلادي لكِ حبي وفؤادي مصر يا أم البلاد أنتِ غايتي والمراد وعلى كل العباد كم لنيلك من أيادي | M15: (Refrain) Biladi, biladi, biladi, laki hubbi wa fu'adi. Biladi, biladi, biladi, laki hubbi wa fu'adi. Misr ya umm al-bilad, inti ghayati wal-murad, wa 'ala kull il-'ibad kam li-Nilik min ayadi. | N15: (Refrain) Ma patrie, ma patrie, ma patrie, à toi mon amour et mon cœur. Ma patrie, ma patrie, ma patrie, à toi mon amour et mon cœur. Égypte, mère de tous les pays, tu es mon espoir et mon ambition, et sur tous les peuples ton Nil a répandu tant de bienfaits. | O15: Oui | P15: Domaine public (texte de 1923) ; vérification : https://fr.wikipedia.org/w/index.php?search=Bilady%2C+Bilady%2C+Bilady&title=Sp%C3%A9cial%3ARecherche&go=Go | Q15: https://commons.wikimedia.org/w/index.php?search=Egypt+national+anthem&title=Special%3AMediaSearch&type=audio | R15: On chante le refrain et la 1re strophe | T15: EG
A16: Afrique | B16: 🇪🇷 | C16: Érythrée | D16: État souverain | E16: ኤርትራ ኤርትራ ኤርትራ (Ertra, Ertra, Ertra) | F16: Érythrée, Érythrée, Érythrée | G16: Solomon Tsehaye Beraki | H16: Isaac Abraham Meharezghi, Aron Tekle Tesfatsion | I16: 1986 | J16: 1986 | K16: 1993 | L16: Non reproduites ici : texte postérieur à 1929, potentiellement protégé — voir la source. | O16: Non | P16: https://fr.wikipedia.org/w/index.php?search=Ertra%2C+Ertra%2C+Ertra&title=Sp%C3%A9cial%3ARecherche&go=Go | Q16: https://commons.wikimedia.org/w/index.php?search=Eritrea+national+anthem&title=Special%3AMediaSearch&type=audio | T16: ER
A17: Afrique | B17: 🇸🇿 | C17: Eswatini | D17: État souverain | E17: Nkulunkulu Mnikati wetibusiso temaSwati | F17: Ô Dieu, dispensateur des bénédictions des Swazis | G17: Andrease Enoke Fanyana Simelane | H17: David Kenneth Rycroft | I17: 1968 | J17: 1968 | K17: 1968 | L17: Non reproduites ici : texte postérieur à 1929, potentiellement protégé — voir la source. | O17: Non | P17: https://fr.wikipedia.org/w/index.php?search=Nkulunkulu+Mnikati+wetibusiso+temaSwati&title=Sp%C3%A9cial%3ARecherche&go=Go | Q17: https://commons.wikimedia.org/w/index.php?search=Eswatini+national+anthem&title=Special%3AMediaSearch&type=audio | T17: SZ
A18: Afrique | B18: 🇪🇹 | C18: Éthiopie | D18: État souverain | E18: ወደፊት ገስግሺ ውድ እናት ኢትዮጵያ (Wedefit Gesgeshi Widd Innat Ityopp'ya) | F18: En avant, chère mère Éthiopie | G18: Dereje Melaku Mengesha | H18: Solomon Lulu Mitiku | I18: 1992 | J18: 1992 | K18: 1992 | L18: Non reproduites ici : texte postérieur à 1929, potentiellement protégé — voir la source. | O18: Non | P18: https://fr.wikipedia.org/w/index.php?search=Wedefit+Gesgeshi+Widd+Innat+Ityopp%27ya&title=Sp%C3%A9cial%3ARecherche&go=Go | Q18: https://commons.wikimedia.org/w/index.php?search=Ethiopia+national+anthem&title=Special%3AMediaSearch&type=audio | T18: ET
A19: Afrique | B19: 🇬🇦 | C19: Gabon | D19: État souverain | E19: La Concorde | F19: La Concorde | G19: Georges Aleka Damas | H19: Georges Aleka Damas | I19: 1960 | J19: 1960 | K19: 1960 | L19: Non reproduites ici : texte postérieur à 1929, potentiellement protégé — voir la source. | O19: Non | P19: https://fr.wikipedia.org/w/index.php?search=La+Concorde&title=Sp%C3%A9cial%3ARecherche&go=Go | Q19: https://commons.wikimedia.org/w/index.php?search=Gabon+national+anthem&title=Special%3AMediaSearch&type=audio | T19: GA
A20: Afrique | B20: 🇬🇲 | C20: Gambie | D20: État souverain | E20: For The Gambia, Our Homeland | F20: Pour la Gambie, notre patrie | G20: Virginia Julie Howe | H20: Jeremy Frederick Howe (sur un air traditionnel mandingue) | I20: 1965 | J20: 1965 | K20: 1965 | L20: Non reproduites ici : texte postérieur à 1929, potentiellement protégé — voir la source. | O20: Non | P20: https://fr.wikipedia.org/w/index.php?search=For+The+Gambia%2C+Our+Homeland&title=Sp%C3%A9cial%3ARecherche&go=Go | Q20: https://commons.wikimedia.org/w/index.php?search=Gambia+national+anthem&title=Special%3AMediaSearch&type=audio | T20: GM
A21: Afrique | B21: 🇬🇭 | C21: Ghana | D21: État souverain | E21: God Bless Our Homeland Ghana | F21: Dieu bénisse notre patrie, le Ghana | G21: Michael Kwame Gbordzoe | H21: Philip Gbeho | I21: 1966 | J21: 1957 | K21: 1957 (paroles 1966) | L21: Non reproduites ici : texte postérieur à 1929, potentiellement protégé — voir la source. | O21: Non | P21: https://fr.wikipedia.org/w/index.php?search=God+Bless+Our+Homeland+Ghana&title=Sp%C3%A9cial%3ARecherche&go=Go | Q21: https://commons.wikimedia.org/w/index.php?search=Ghana+national+anthem&title=Special%3AMediaSearch&type=audio | T21: GH
A22: Afrique | B22: 🇬🇳 | C22: Guinée | D22: État souverain | E22: Liberté | F22: Liberté | G22: Jean Celestin Traoré | H22: Fodéba Keïta (sur l'air « Alpha Yaya ») | I22: 1958 | J22: 1958 | K22: 1958 | L22: Non reproduites ici : texte postérieur à 1929, potentiellement protégé — voir la source. | O22: Non | P22: https://fr.wikipedia.org/w/index.php?search=Libert%C3%A9&title=Sp%C3%A9cial%3ARecherche&go=Go | Q22: https://commons.wikimedia.org/w/index.php?search=Guinea+national+anthem&title=Special%3AMediaSearch&type=audio | T22: GN
A23: Afrique | B23: 🇬🇶 | C23: Guinée équatoriale | D23: État souverain | E23: Caminemos pisando las sendas | F23: Marchons sur les sentiers | G23: Atanasio Ndongo Miyone | H23: Ramírez Ortiz | I23: 1968 | J23: 1968 | K23: 1968 | L23: Non reproduites ici : texte postérieur à 1929, potentiellement protégé — voir la source. | O23: Non | P23: https://fr.wikipedia.org/w/index.php?search=Caminemos+pisando+las+sendas&title=Sp%C3%A9cial%3ARecherche&go=Go | Q23: https://commons.wikimedia.org/w/index.php?search=Equatorial+Guinea+national+anthem&title=Special%3AMediaSearch&type=audio | T23: GQ
A24: Afrique | B24: 🇬🇼 | C24: Guinée-Bissau | D24: État souverain | E24: Esta é a Nossa Pátria Bem Amada | F24: Voici notre patrie bien-aimée | G24: Amílcar Cabral | H24: Xiao He | I24: 1963 | J24: 1963 | K24: 1974 | L24: Non reproduites ici : texte postérieur à 1929, potentiellement protégé — voir la source. | O24: Non | P24: https://fr.wikipedia.org/w/index.php?search=Esta+%C3%A9+a+Nossa+P%C3%A1tria+Bem+Amada&title=Sp%C3%A9cial%3ARecherche&go=Go | Q24: https://commons.wikimedia.org/w/index.php?search=Guinea-Bissau+national+anthem&title=Special%3AMediaSearch&type=audio | T24: GW
A25: Afrique | B25: 🇲🇺 | C25: Île Maurice | D25: État souverain | E25: Motherland | F25: Mère patrie | G25: Jean-Georges Prosper | H25: Philippe Gentil | I25: 1968 | J25: 1968 | K25: 1968 | L25: Non reproduites ici : texte postérieur à 1929, potentiellement protégé — voir la source. | O25: Non | P25: https://fr.wikipedia.org/w/index.php?search=Motherland&title=Sp%C3%A9cial%3ARecherche&go=Go | Q25: https://commons.wikimedia.org/w/index.php?search=Mauritius+national+anthem&title=Special%3AMediaSearch&type=audio | T25: MU
A26: Afrique | B26: 🇨🇻 | C26: Îles du Cap-Vert | D26: État souverain | E26: Cântico da Liberdade | F26: Cantique de la liberté | G26: Amílcar Spencer Lopes | H26: Adalberto Higino Tavares Silva | I26: 1996 | J26: 1996 | K26: 1996 | L26: Non reproduites ici : texte postérieur à 1929, potentiellement protégé — voir la source. | O26: Non | P26: https://fr.wikipedia.org/w/index.php?search=C%C3%A2ntico+da+Liberdade&title=Sp%C3%A9cial%3ARecherche&go=Go | Q26: https://commons.wikimedia.org/w/index.php?search=Cape+Verde+national+anthem&title=Special%3AMediaSearch&type=audio | T26: CV
A27: Afrique | B27: 🇰🇪 | C27: Kenya | D27: État souverain | E27: Ee Mungu Nguvu Yetu | F27: Ô Dieu de toute création | G27: commission nationale | H27: mélodie traditionnelle pokomo | I27: 1963 | J27: traditionnelle | K27: 1963 | L27: Non reproduites ici : texte postérieur à 1929, potentiellement protégé — voir la source. | O27: Non | P27: https://fr.wikipedia.org/w/index.php?search=Ee+Mungu+Nguvu+Yetu&title=Sp%C3%A9cial%3ARecherche&go=Go | Q27: https://commons.wikimedia.org/w/index.php?search=Kenya+national+anthem&title=Special%3AMediaSearch&type=audio | T27: KE
A28: Afrique | B28: 🇱🇸 | C28: Lesotho | D28: État souverain | E28: Lesotho Fatše La Bo-ntat'a Rona | F28: Lesotho, terre de nos pères | G28: François Coillard | H28: Ferdinand-Samuel Laur | I28: 1869 | J28: 1823 | K28: 1967 | L28: Lesotho fatše la bo-ntat'a rona, Har'a mafatše le letle ke lona. Ke moo re hlahileng, Ke moo re holileng, Rea le rata. Molimo aku boloke Lesotho, U felise lintoa le matšoenyeho. Oho fatše lena, La bo-ntat'a rona, Le be le khotso. | M28: — (écriture latine) | N28: Lesotho, terre de nos pères, de tous les pays, tu es le plus beau. C'est là que nous sommes nés, c'est là que nous avons grandi, nous t'aimons. Dieu, protège le Lesotho, mets fin aux guerres et aux tourments. Ô cette terre, terre de nos pères, qu'elle soit en paix. | O28: Oui | P28: Domaine public (texte de 1869) ; vérification : https://fr.wikipedia.org/w/index.php?search=Lesotho+Fat%C5%A1e+La+Bo-ntat%27a+Rona&title=Sp%C3%A9cial%3ARecherche&go=Go | Q28: https://commons.wikimedia.org/w/index.php?search=Lesotho+national+anthem&title=Special%3AMediaSearch&type=audio | T28: LS
A29: Afrique | B29: 🇱🇷 | C29: Liberia | D29: État souverain | E29: All Hail, Liberia, Hail! | F29: Salut, Liberia, salut ! | G29: Daniel Bashiel Warner | H29: Olmstead Luca | I29: 1847 | J29: 1860 | K29: 1847 | L29: All hail, Liberia, hail! (All hail!) All hail, Liberia, hail! (All hail!) This glorious land of liberty Shall long be ours. Though new her name, Green be her fame, And mighty be her powers, And mighty be her powers. In joy and gladness With our hearts united, We'll shout the freedom Of a race benighted, Long live Liberia, happy land! A home of glorious liberty, By God's command! A home of glorious liberty, By God's command! | M29: — (écriture latine) | N29: Salut, Liberia, salut ! (Salut !) Salut, Liberia, salut ! (Salut !) Cette glorieuse terre de liberté sera longtemps nôtre. Bien que son nom soit nouveau, que sa renommée soit florissante et sa puissance grande, et sa puissance grande. Dans la joie et l'allégresse, les cœurs unis, nous proclamerons la liberté d'une race longtemps plongée dans les ténèbres. Vive le Liberia, terre heureuse ! Demeure d'une glorieuse liberté, par la volonté de Dieu ! Demeure d'une glorieuse liberté, par la volonté de Dieu ! | O29: Oui | P29: Domaine public (texte de 1847) ; vérification : https://fr.wikipedia.org/w/index.php?search=All+Hail%2C+Liberia%2C+Hail%21&title=Sp%C3%A9cial%3ARecherche&go=Go | Q29: https://commons.wikimedia.org/w/index.php?search=Liberia+national+anthem&title=Special%3AMediaSearch&type=audio | T29: LR
A30: Afrique | B30: 🇱🇾 | C30: Libye | D30: État souverain | E30: ليبيا ليبيا ليبيا (Libya, Libya, Libya) | F30: Libye, Libye, Libye | G30: Al Bashir Al Arebi | H30: Mohammed Abdel Wahab | I30: 1951 | J30: 1951 | K30: 1951 (rétabli 2011) | L30: Non reproduites ici : texte postérieur à 1929, potentiellement protégé — voir la source. | O30: Non | P30: https://fr.wikipedia.org/w/index.php?search=Libya%2C+Libya%2C+Libya&title=Sp%C3%A9cial%3ARecherche&go=Go | Q30: https://commons.wikimedia.org/w/index.php?search=Libya+national+anthem&title=Special%3AMediaSearch&type=audio | T30: LY
A31: Afrique | B31: 🇲🇬 | C31: Madagascar | D31: État souverain | E31: Ry Tanindrazanay malala ô! | F31: Ô notre chère patrie | G31: Pasteur Rahajason | H31: Norbert Raharisoa | I31: 1958 | J31: 1958 | K31: 1959 | L31: Non reproduites ici : texte postérieur à 1929, potentiellement protégé — voir la source. | O31: Non | P31: https://fr.wikipedia.org/w/index.php?search=Ry+Tanindrazanay+malala+%C3%B4%21&title=Sp%C3%A9cial%3ARecherche&go=Go | Q31: https://commons.wikimedia.org/w/index.php?search=Madagascar+national+anthem&title=Special%3AMediaSearch&type=audio | T31: MG
A32: Afrique | B32: 🇲🇼 | C32: Malawi | D32: État souverain | E32: Mlungu dalitsani Malaŵi | F32: Ô Dieu, bénis notre terre du Malawi | G32: Michael-Fredrick Paul Sauka | H32: Michael-Fredrick Paul Sauka | I32: 1964 | J32: 1964 | K32: 1964 | L32: Non reproduites ici : texte postérieur à 1929, potentiellement protégé — voir la source. | O32: Non | P32: https://fr.wikipedia.org/w/index.php?search=Mlungu+dalitsani+Mala%C5%B5i&title=Sp%C3%A9cial%3ARecherche&go=Go | Q32: https://commons.wikimedia.org/w/index.php?search=Malawi+national+anthem&title=Special%3AMediaSearch&type=audio | T32: MW
A33: Afrique | B33: 🇲🇱 | C33: Mali | D33: État souverain | E33: Le Mali | F33: Le Mali | G33: Seydou Badian Kouyaté | H33: Banzoumana Sissoko | I33: 1962 | J33: 1962 | K33: 1962 | L33: Non reproduites ici : texte postérieur à 1929, potentiellement protégé — voir la source. | O33: Non | P33: https://fr.wikipedia.org/w/index.php?search=Le+Mali&title=Sp%C3%A9cial%3ARecherche&go=Go | Q33: https://commons.wikimedia.org/w/index.php?search=Mali+national+anthem&title=Special%3AMediaSearch&type=audio | T33: ML
A34: Afrique | B34: 🇲🇦 | C34: Maroc | D34: État souverain | E34: النشيد الوطني المغربي (Hymne chérifien) | F34: Hymne chérifien | G34: Ali Squalli Houssaini | H34: Léo Morgan | I34: 1970 | J34: 1956 | K34: 1956 (paroles 1970) | L34: Non reproduites ici : texte postérieur à 1929, potentiellement protégé — voir la source. | O34: Non | P34: https://fr.wikipedia.org/w/index.php?search=Hymne+ch%C3%A9rifien&title=Sp%C3%A9cial%3ARecherche&go=Go | Q34: https://commons.wikimedia.org/w/index.php?search=Morocco+national+anthem&title=Special%3AMediaSearch&type=audio | T34: MA
A35: Afrique | B35: 🇲🇷 | C35: Mauritanie | D35: État souverain | E35: بلادِ الإباءِ (Bilādu-l-ʾibāʾi) | F35: Pays des fiers | G35: collectif | H35: Rajeh Daoud | I35: 2017 | J35: 2017 | K35: 2017 | L35: Non reproduites ici : texte postérieur à 1929, potentiellement protégé — voir la source. | O35: Non | P35: https://fr.wikipedia.org/w/index.php?search=Bil%C4%81du-l-%CA%BEib%C4%81%CA%BEi&title=Sp%C3%A9cial%3ARecherche&go=Go | Q35: https://commons.wikimedia.org/w/index.php?search=Mauritania+national+anthem&title=Special%3AMediaSearch&type=audio | R35: Remplace l'hymne de 1960 (à vérifier) | T35: MR
A36: Afrique | B36: 🇾🇹 | C36: Mayotte | D36: Territoire / dépendance (France) | E36: La Marseillaise | F36: La Marseillaise | G36: Claude Joseph Rouget de Lisle | H36: Claude Joseph Rouget de Lisle | I36: 1792 | J36: 1792 | K36: 1795 (définitivement 1879) | L36: Allons enfants de la Patrie, Le jour de gloire est arrivé ! Contre nous de la tyrannie L'étendard sanglant est levé, (bis) Entendez-vous dans les campagnes Mugir ces féroces soldats ? Ils viennent jusque dans vos bras Égorger vos fils, vos compagnes ! Aux armes, citoyens, Formez vos bataillons, Marchons, marchons ! Qu'un sang impur Abreuve nos sillons ! | M36: — (écriture latine) | N36: — (texte original en français) | O36: Oui | P36: Domaine public (texte de 1792) ; vérification : https://fr.wikipedia.org/w/index.php?search=La+Marseillaise&title=Sp%C3%A9cial%3ARecherche&go=Go | Q36: https://commons.wikimedia.org/w/index.php?search=France+national+anthem&title=Special%3AMediaSearch&type=audio | R36: Département et région d'outre-mer français — utilise l'hymne de : France | T36: YT
A37: Afrique | B37: 🇲🇿 | C37: Mozambique | D37: État souverain | E37: Pátria Amada | F37: Patrie bien-aimée | G37: Salomão J. Manhiça (collectif) | H37: Justino Sigaulane Chemane | I37: 2002 | J37: 2002 | K37: 2002 | L37: Non reproduites ici : texte postérieur à 1929, potentiellement protégé — voir la source. | O37: Non | P37: https://fr.wikipedia.org/w/index.php?search=P%C3%A1tria+Amada&title=Sp%C3%A9cial%3ARecherche&go=Go | Q37: https://commons.wikimedia.org/w/index.php?search=Mozambique+national+anthem&title=Special%3AMediaSearch&type=audio | T37: MZ
A38: Afrique | B38: 🇳🇦 | C38: Namibie | D38: État souverain | E38: Namibia, Land of the Brave | F38: Namibie, terre des braves | G38: Axali Doëseb | H38: Axali Doëseb | I38: 1991 | J38: 1991 | K38: 1991 | L38: Non reproduites ici : texte postérieur à 1929, potentiellement protégé — voir la source. | O38: Non | P38: https://fr.wikipedia.org/w/index.php?search=Namibia%2C+Land+of+the+Brave&title=Sp%C3%A9cial%3ARecherche&go=Go | Q38: https://commons.wikimedia.org/w/index.php?search=Namibia+national+anthem&title=Special%3AMediaSearch&type=audio | T38: NA
A39: Afrique | B39: 🇳🇪 | C39: Niger | D39: État souverain | E39: L'Honneur de la Patrie | F39: L'Honneur de la Patrie | G39: collectif | H39: collectif | I39: 2023 | J39: 2023 | K39: 2023 | L39: Non reproduites ici : texte postérieur à 1929, potentiellement protégé — voir la source. | O39: Non | P39: https://fr.wikipedia.org/w/index.php?search=L%27Honneur+de+la+Patrie&title=Sp%C3%A9cial%3ARecherche&go=Go | Q39: https://commons.wikimedia.org/w/index.php?search=Niger+national+anthem&title=Special%3AMediaSearch&type=audio | R39: Remplace « La Nigérienne » (1961) (à vérifier) | T39: NE
A40: Afrique | B40: 🇳🇬 | C40: Nigéria | D40: État souverain | E40: Nigeria, We Hail Thee | F40: Nigeria, nous te saluons | G40: Lillian Jean Williams | H40: Frances Berda | I40: 1960 | J40: 1960 | K40: 1960 (rétabli en 2024) | L40: Non reproduites ici : texte postérieur à 1929, potentiellement protégé — voir la source. | O40: Non | P40: https://fr.wikipedia.org/w/index.php?search=Nigeria%2C+We+Hail+Thee&title=Sp%C3%A9cial%3ARecherche&go=Go | Q40: https://commons.wikimedia.org/w/index.php?search=Nigeria+national+anthem&title=Special%3AMediaSearch&type=audio | R40: Remplace « Arise, O Compatriots » (1978-2024) | T40: NG
A41: Afrique | B41: 🇺🇬 | C41: Ouganda | D41: État souverain | E41: Oh Uganda, Land of Beauty | F41: Ô Ouganda, terre de beauté | G41: George Wilberforce Kakoma | H41: George Wilberforce Kakoma | I41: 1962 | J41: 1962 | K41: 1962 | L41: Non reproduites ici : texte postérieur à 1929, potentiellement protégé — voir la source. | O41: Non | P41: https://fr.wikipedia.org/w/index.php?search=Oh+Uganda%2C+Land+of+Beauty&title=Sp%C3%A9cial%3ARecherche&go=Go | Q41: https://commons.wikimedia.org/w/index.php?search=Uganda+national+anthem&title=Special%3AMediaSearch&type=audio | T41: UG
A42: Afrique | B42: 🇨🇫 | C42: République centrafricaine | D42: État souverain | E42: La Renaissance | F42: La Renaissance | G42: Barthélemy Boganda | H42: Herbert Pepper | I42: 1960 | J42: 1960 | K42: 1960 | L42: Non reproduites ici : texte postérieur à 1929, potentiellement protégé — voir la source. | O42: Non | P42: https://fr.wikipedia.org/w/index.php?search=La+Renaissance&title=Sp%C3%A9cial%3ARecherche&go=Go | Q42: https://commons.wikimedia.org/w/index.php?search=Central+African+Republic+national+anthem&title=Special%3AMediaSearch&type=audio | T42: CF
A43: Afrique | B43: 🇷🇪 | C43: Réunion | D43: Territoire / dépendance (France) | E43: La Marseillaise | F43: La Marseillaise | G43: Claude Joseph Rouget de Lisle | H43: Claude Joseph Rouget de Lisle | I43: 1792 | J43: 1792 | K43: 1795 (définitivement 1879) | L43: Allons enfants de la Patrie, Le jour de gloire est arrivé ! Contre nous de la tyrannie L'étendard sanglant est levé, (bis) Entendez-vous dans les campagnes Mugir ces féroces soldats ? Ils viennent jusque dans vos bras Égorger vos fils, vos compagnes ! Aux armes, citoyens, Formez vos bataillons, Marchons, marchons ! Qu'un sang impur Abreuve nos sillons ! | M43: — (écriture latine) | N43: — (texte original en français) | O43: Oui | P43: Domaine public (texte de 1792) ; vérification : https://fr.wikipedia.org/w/index.php?search=La+Marseillaise&title=Sp%C3%A9cial%3ARecherche&go=Go | Q43: https://commons.wikimedia.org/w/index.php?search=France+national+anthem&title=Special%3AMediaSearch&type=audio | R43: Département et région d'outre-mer français — utilise l'hymne de : France | T43: RE
A44: Afrique | B44: 🇷🇼 | C44: Rwanda | D44: État souverain | E44: Rwanda Nziza | F44: Beau Rwanda | G44: Faustin Murigo | H44: Jean-Bosco Hashakaimana | I44: 2001 | J44: 2001 | K44: 2001 | L44: Non reproduites ici : texte postérieur à 1929, potentiellement protégé — voir la source. | O44: Non | P44: https://fr.wikipedia.org/w/index.php?search=Rwanda+Nziza&title=Sp%C3%A9cial%3ARecherche&go=Go | Q44: https://commons.wikimedia.org/w/index.php?search=Rwanda+national+anthem&title=Special%3AMediaSearch&type=audio | T44: RW
A45: Afrique | B45: 🇪🇭 | C45: Sahara Occidental | D45: État à reconnaissance limitée | E45: يا بني الصحراء (Yā Banī as-Saharā) | F45: Ô fils du Sahara | G45: inconnu | H45: inconnu | I45: 1979 | J45: 1979 | K45: 1979 | L45: Non reproduites ici : texte postérieur à 1929, potentiellement protégé — voir la source. | O45: Non | P45: https://fr.wikipedia.org/w/index.php?search=Y%C4%81+Ban%C4%AB+as-Sahar%C4%81&title=Sp%C3%A9cial%3ARecherche&go=Go | Q45: https://commons.wikimedia.org/w/index.php?search=Western+Sahara+national+anthem&title=Special%3AMediaSearch&type=audio | R45: Hymne de la République arabe sahraouie démocratique (à vérifier) | T45: EH
A46: Afrique | B46: 🇸🇭 | C46: Sainte-Hélène, Ascension et Tristan da Cunha | D46: Territoire / dépendance (Royaume-Uni) | E46: God Save the King | F46: Dieu protège le Roi | G46: anonyme | H46: anonyme | I46: vers 1745 | J46: vers 1745 | K46: — (usage coutumier depuis le XVIIIe s.) | L46: God save our gracious King! Long live our noble King! God save the King! Send him victorious, Happy and glorious, Long to reign over us, God save the King! | M46: — (écriture latine) | N46: Dieu protège notre gracieux Roi ! Longue vie à notre noble Roi ! Dieu protège le Roi ! Rends-le victorieux, Heureux et glorieux, Qu'il règne longtemps sur nous, Dieu protège le Roi ! | O46: Oui | P46: Domaine public (texte de vers 1745) ; vérification : https://fr.wikipedia.org/w/index.php?search=God+Save+the+King&title=Sp%C3%A9cial%3ARecherche&go=Go | Q46: https://commons.wikimedia.org/w/index.php?search=United+Kingdom+national+anthem&title=Special%3AMediaSearch&type=audio | R46: Territoire britannique d'outre-mer — utilise l'hymne de : Royaume-Uni | T46: SH
A47: Afrique | B47: 🇸🇹 | C47: São Tomé et Príncipe | D47: État souverain | E47: Independência total | F47: Indépendance totale | G47: Alda Neves da Graça do Espírito Santo | H47: Manuel dos Santos Barreto de Sousa e Almeida | I47: 1975 | J47: 1975 | K47: 1975 | L47: Non reproduites ici : texte postérieur à 1929, potentiellement protégé — voir la source. | O47: Non | P47: https://fr.wikipedia.org/w/index.php?search=Independ%C3%AAncia+total&title=Sp%C3%A9cial%3ARecherche&go=Go | Q47: https://commons.wikimedia.org/w/index.php?search=S%C3%A3o+Tom%C3%A9+and+Pr%C3%ADncipe+national+anthem&title=Special%3AMediaSearch&type=audio | T47: ST
A48: Afrique | B48: 🇸🇳 | C48: Sénégal | D48: État souverain | E48: Le Lion rouge | F48: Le Lion rouge | G48: Léopold Sédar Senghor | H48: Herbert Pepper | I48: 1960 | J48: 1960 | K48: 1960 | L48: Non reproduites ici : texte postérieur à 1929, potentiellement protégé — voir la source. | O48: Non | P48: https://fr.wikipedia.org/w/index.php?search=Le+Lion+rouge&title=Sp%C3%A9cial%3ARecherche&go=Go | Q48: https://commons.wikimedia.org/w/index.php?search=Senegal+national+anthem&title=Special%3AMediaSearch&type=audio | T48: SN
A49: Afrique | B49: 🇸🇨 | C49: Seychelles | D49: État souverain | E49: Koste Seselwa | F49: Unissons-nous, Seychellois | G49: David François Marc André, George Charles Robert Payet | H49: David François Marc André, George Charles Robert Payet | I49: 1996 | J49: 1996 | K49: 1996 | L49: Non reproduites ici : texte postérieur à 1929, potentiellement protégé — voir la source. | O49: Non | P49: https://fr.wikipedia.org/w/index.php?search=Koste+Seselwa&title=Sp%C3%A9cial%3ARecherche&go=Go | Q49: https://commons.wikimedia.org/w/index.php?search=Seychelles+national+anthem&title=Special%3AMediaSearch&type=audio | T49: SC
A50: Afrique | B50: 🇸🇱 | C50: Sierra Leone | D50: État souverain | E50: High We Exalt Thee, Realm of the Free | F50: Nous t'exaltons, royaume des libres | G50: Clifford Nelson Fyle | H50: John Joseph Akar | I50: 1961 | J50: 1961 | K50: 1961 | L50: Non reproduites ici : texte postérieur à 1929, potentiellement protégé — voir la source. | O50: Non | P50: https://fr.wikipedia.org/w/index.php?search=High+We+Exalt+Thee%2C+Realm+of+the+Free&title=Sp%C3%A9cial%3ARecherche&go=Go | Q50: https://commons.wikimedia.org/w/index.php?search=Sierra+Leone+national+anthem&title=Special%3AMediaSearch&type=audio | T50: SL
A51: Afrique | B51: 🇸🇴 | C51: Somalie | D51: État souverain | E51: Qolobaa Calankeed | F51: Chaque nation a son drapeau | G51: Abdullahi Qarshe | H51: Abdullahi Qarshe | I51: 1959 | J51: 1959 | K51: 2012 | L51: Non reproduites ici : texte postérieur à 1929, potentiellement protégé — voir la source. | O51: Non | P51: https://fr.wikipedia.org/w/index.php?search=Qolobaa+Calankeed&title=Sp%C3%A9cial%3ARecherche&go=Go | Q51: https://commons.wikimedia.org/w/index.php?search=Somalia+national+anthem&title=Special%3AMediaSearch&type=audio | T51: SO
A52: Afrique | B52: 🇸🇩 | C52: Soudan | D52: État souverain | E52: نحن جند الله جند الوطن (Nahnu Jund Allah Jund al-Watan) | F52: Nous sommes les soldats de Dieu et de la patrie | G52: Ahmed Mohammed Salih | H52: Ahmed Murjan | I52: 1955 | J52: 1955 | K52: 1956 | L52: Non reproduites ici : texte postérieur à 1929, potentiellement protégé — voir la source. | O52: Non | P52: https://fr.wikipedia.org/w/index.php?search=Nahnu+Jund+Allah+Jund+al-Watan&title=Sp%C3%A9cial%3ARecherche&go=Go | Q52: https://commons.wikimedia.org/w/index.php?search=Sudan+national+anthem&title=Special%3AMediaSearch&type=audio | T52: SD
A53: Afrique | B53: 🇸🇸 | C53: Soudan du Sud | D53: État souverain | E53: South Sudan Oyee! | F53: Soudan du Sud, hourra ! | G53: collectif | H53: Université de Juba (collectif) | I53: 2011 | J53: 2011 | K53: 2011 | L53: Non reproduites ici : texte postérieur à 1929, potentiellement protégé — voir la source. | O53: Non | P53: https://fr.wikipedia.org/w/index.php?search=South+Sudan+Oyee%21&title=Sp%C3%A9cial%3ARecherche&go=Go | Q53: https://commons.wikimedia.org/w/index.php?search=South+Sudan+national+anthem&title=Special%3AMediaSearch&type=audio | T53: SS
A54: Afrique | B54: 🇹🇿 | C54: Tanzanie | D54: État souverain | E54: Mungu ibariki Afrika | F54: Dieu bénisse l'Afrique | G54: collectif | H54: Enoch Sontonga | I54: 1961 | J54: 1897 | K54: 1961 | L54: Non reproduites ici : texte postérieur à 1929, potentiellement protégé — voir la source. | O54: Non | P54: https://fr.wikipedia.org/w/index.php?search=Mungu+ibariki+Afrika&title=Sp%C3%A9cial%3ARecherche&go=Go | Q54: https://commons.wikimedia.org/w/index.php?search=Tanzania+national+anthem&title=Special%3AMediaSearch&type=audio | T54: TZ
A55: Afrique | B55: 🇹🇩 | C55: Tchad | D55: État souverain | E55: La Tchadienne | F55: La Tchadienne | G55: Louis Gidrol et ses élèves | H55: Paul Villard | I55: 1960 | J55: 1960 | K55: 1960 | L55: Non reproduites ici : texte postérieur à 1929, potentiellement protégé — voir la source. | O55: Non | P55: https://fr.wikipedia.org/w/index.php?search=La+Tchadienne&title=Sp%C3%A9cial%3ARecherche&go=Go | Q55: https://commons.wikimedia.org/w/index.php?search=Chad+national+anthem&title=Special%3AMediaSearch&type=audio | T55: TD
A56: Afrique | B56: 🇹🇫 | C56: Terres australes et antarctiques françaises | D56: Territoire / dépendance (France) | E56: La Marseillaise | F56: La Marseillaise | G56: Claude Joseph Rouget de Lisle | H56: Claude Joseph Rouget de Lisle | I56: 1792 | J56: 1792 | K56: 1795 (définitivement 1879) | L56: Allons enfants de la Patrie, Le jour de gloire est arrivé ! Contre nous de la tyrannie L'étendard sanglant est levé, (bis) Entendez-vous dans les campagnes Mugir ces féroces soldats ? Ils viennent jusque dans vos bras Égorger vos fils, vos compagnes ! Aux armes, citoyens, Formez vos bataillons, Marchons, marchons ! Qu'un sang impur Abreuve nos sillons ! | M56: — (écriture latine) | N56: — (texte original en français) | O56: Oui | P56: Domaine public (texte de 1792) ; vérification : https://fr.wikipedia.org/w/index.php?search=La+Marseillaise&title=Sp%C3%A9cial%3ARecherche&go=Go | Q56: https://commons.wikimedia.org/w/index.php?search=France+national+anthem&title=Special%3AMediaSearch&type=audio | R56: Terres australes et antarctiques françaises (sans population permanente) — utilise l'hymne de : France | T56: TF
A57: Afrique | B57: 🇮🇴 | C57: Territoire britannique de l'océan Indien | D57: Territoire / dépendance (Royaume-Uni) | E57: God Save the King | F57: Dieu protège le Roi | G57: anonyme | H57: anonyme | I57: vers 1745 | J57: vers 1745 | K57: — (usage coutumier depuis le XVIIIe s.) | L57: God save our gracious King! Long live our noble King! God save the King! Send him victorious, Happy and glorious, Long to reign over us, God save the King! | M57: — (écriture latine) | N57: Dieu protège notre gracieux Roi ! Longue vie à notre noble Roi ! Dieu protège le Roi ! Rends-le victorieux, Heureux et glorieux, Qu'il règne longtemps sur nous, Dieu protège le Roi ! | O57: Oui | P57: Domaine public (texte de vers 1745) ; vérification : https://fr.wikipedia.org/w/index.php?search=God+Save+the+King&title=Sp%C3%A9cial%3ARecherche&go=Go | Q57: https://commons.wikimedia.org/w/index.php?search=United+Kingdom+national+anthem&title=Special%3AMediaSearch&type=audio | R57: Territoire britannique d'outre-mer — utilise l'hymne de : Royaume-Uni | T57: IO
A58: Afrique | B58: 🇹🇬 | C58: Togo | D58: État souverain | E58: Salut à toi, pays de nos aïeux | F58: Salut à toi, pays de nos aïeux | G58: Alex Casimir-Dosseh | H58: Alex Casimir-Dosseh | I58: 1960 | J58: 1960 | K58: 1960 (rétabli 1992) | L58: Non reproduites ici : texte postérieur à 1929, potentiellement protégé — voir la source. | O58: Non | P58: https://fr.wikipedia.org/w/index.php?search=Salut+%C3%A0+toi%2C+pays+de+nos+a%C3%AFeux&title=Sp%C3%A9cial%3ARecherche&go=Go | Q58: https://commons.wikimedia.org/w/index.php?search=Togo+national+anthem&title=Special%3AMediaSearch&type=audio | T58: TG
A59: Afrique | B59: 🇹🇳 | C59: Tunisie | D59: État souverain | E59: حماة الحمى (Humat al-Hima) | F59: Défenseurs de la patrie | G59: Mostafa Saadeq Al-Rafe'ie, Aboul-Qacem Chebbi | H59: attribuée à Mohammed Abdel Wahab | I59: 1930 / 1933 | J59: 1930 | K59: 1987 | L59: Non reproduites ici : texte postérieur à 1929, potentiellement protégé — voir la source. | O59: Non | P59: https://fr.wikipedia.org/w/index.php?search=Humat+al-Hima&title=Sp%C3%A9cial%3ARecherche&go=Go | Q59: https://commons.wikimedia.org/w/index.php?search=Tunisia+national+anthem&title=Special%3AMediaSearch&type=audio | T59: TN
A60: Afrique | B60: 🇿🇲 | C60: Zambie | D60: État souverain | E60: Stand and Sing of Zambia, Proud and Free / Lumbanyeni Zambia | F60: Debout, chantons la Zambie | G60: collectif | H60: Enoch Sontonga | I60: 1964 | J60: 1897 | K60: 1964 | L60: Non reproduites ici : texte postérieur à 1929, potentiellement protégé — voir la source. | O60: Non | P60: https://fr.wikipedia.org/w/index.php?search=Stand+and+Sing+of+Zambia%2C+Proud+and+Free&title=Sp%C3%A9cial%3ARecherche&go=Go | Q60: https://commons.wikimedia.org/w/index.php?search=Zambia+national+anthem&title=Special%3AMediaSearch&type=audio | T60: ZM
A61: Afrique | B61: 🇿🇼 | C61: Zimbabwe | D61: État souverain | E61: Simudzai Mureza wedu weZimbabwe | F61: Levez haut le drapeau du Zimbabwe | G61: Solomon Mutswairo | H61: Fred Changundega | I61: 1994 | J61: 1994 | K61: 1994 | L61: Non reproduites ici : texte postérieur à 1929, potentiellement protégé — voir la source. | O61: Non | P61: https://fr.wikipedia.org/w/index.php?search=Simudzai+Mureza+wedu+weZimbabwe&title=Sp%C3%A9cial%3ARecherche&go=Go | Q61: https://commons.wikimedia.org/w/index.php?search=Zimbabwe+national+anthem&title=Special%3AMediaSearch&type=audio | T61: ZW
A62: Amérique du Nord | B62: 🇦🇮 | C62: Anguilla | D62: Territoire / dépendance (Royaume-Uni) | E62: God Save the King | F62: Dieu protège le Roi | G62: anonyme | H62: anonyme | I62: vers 1745 | J62: vers 1745 | K62: — (usage coutumier depuis le XVIIIe s.) | L62: God save our gracious King! Long live our noble King! God save the King! Send him victorious, Happy and glorious, Long to reign over us, God save the King! | M62: — (écriture latine) | N62: Dieu protège notre gracieux Roi ! Longue vie à notre noble Roi ! Dieu protège le Roi ! Rends-le victorieux, Heureux et glorieux, Qu'il règne longtemps sur nous, Dieu protège le Roi ! | O62: Oui | P62: Domaine public (texte de vers 1745) ; vérification : https://fr.wikipedia.org/w/index.php?search=God+Save+the+King&title=Sp%C3%A9cial%3ARecherche&go=Go | Q62: https://commons.wikimedia.org/w/index.php?search=United+Kingdom+national+anthem&title=Special%3AMediaSearch&type=audio | R62: Territoire britannique d'outre-mer ; chant local « God Bless Anguilla » — utilise l'hymne de : Royaume-Uni | T62: AI
A63: Amérique du Nord | B63: 🇦🇬 | C63: Antigua-et-Barbuda | D63: État souverain | E63: Fair Antigua, We Salute Thee | F63: Belle Antigua, nous te saluons | G63: Novelle Hamilton Richards | H63: Walter Garnet Picart Chambers | I63: 1967 | J63: 1967 | K63: 1981 | L63: Non reproduites ici : texte postérieur à 1929, potentiellement protégé — voir la source. | O63: Non | P63: https://fr.wikipedia.org/w/index.php?search=Fair+Antigua%2C+We+Salute+Thee&title=Sp%C3%A9cial%3ARecherche&go=Go | Q63: https://commons.wikimedia.org/w/index.php?search=Antigua+and+Barbuda+national+anthem&title=Special%3AMediaSearch&type=audio | T63: AG
A64: Amérique du Nord | B64: 🇦🇼 | C64: Aruba | D64: Territoire / dépendance | E64: Aruba Dushi Tera | F64: Aruba, douce terre | G64: Juan Chabaya Lampe | H64: Juan Chabaya Lampe, Rufo Wever | I64: années 1950 | J64: années 1950 | K64: 1976 | L64: Non reproduites ici : texte postérieur à 1929, potentiellement protégé — voir la source. | O64: Non | P64: https://fr.wikipedia.org/w/index.php?search=Aruba+Dushi+Tera&title=Sp%C3%A9cial%3ARecherche&go=Go | Q64: https://commons.wikimedia.org/w/index.php?search=Aruba+national+anthem&title=Special%3AMediaSearch&type=audio | R64: Pays constitutif du Royaume des Pays-Bas | T64: AW
A65: Amérique du Nord | B65: 🇧🇸 | C65: Bahamas | D65: État souverain | E65: March On, Bahamaland | F65: En avant, Bahamas | G65: Timothy Gibson | H65: Timothy Gibson | I65: 1973 | J65: 1973 | K65: 1973 | L65: Non reproduites ici : texte postérieur à 1929, potentiellement protégé — voir la source. | O65: Non | P65: https://fr.wikipedia.org/w/index.php?search=March+On%2C+Bahamaland&title=Sp%C3%A9cial%3ARecherche&go=Go | Q65: https://commons.wikimedia.org/w/index.php?search=Bahamas+national+anthem&title=Special%3AMediaSearch&type=audio | T65: BS
A66: Amérique du Nord | B66: 🇧🇧 | C66: Barbade | D66: État souverain | E66: In Plenty and In Time of Need | F66: Dans l'abondance et le besoin | G66: Irving Burgie | H66: C. Van Roland Edwards | I66: 1966 | J66: 1966 | K66: 1966 | L66: Non reproduites ici : texte postérieur à 1929, potentiellement protégé — voir la source. | O66: Non | P66: https://fr.wikipedia.org/w/index.php?search=In+Plenty+and+In+Time+of+Need&title=Sp%C3%A9cial%3ARecherche&go=Go | Q66: https://commons.wikimedia.org/w/index.php?search=Barbados+national+anthem&title=Special%3AMediaSearch&type=audio | T66: BB
A67: Amérique du Nord | B67: 🇧🇿 | C67: Belize | D67: État souverain | E67: Land of the Free | F67: Terre des libres | G67: Samuel Alfred Haynes | H67: Selwyn Walford Young | I67: 1963 | J67: 1963 | K67: 1981 | L67: Non reproduites ici : texte postérieur à 1929, potentiellement protégé — voir la source. | O67: Non | P67: https://fr.wikipedia.org/w/index.php?search=Land+of+the+Free&title=Sp%C3%A9cial%3ARecherche&go=Go | Q67: https://commons.wikimedia.org/w/index.php?search=Belize+national+anthem&title=Special%3AMediaSearch&type=audio | T67: BZ
A68: Amérique du Nord | B68: 🇧🇲 | C68: Bermudes | D68: Territoire / dépendance (Royaume-Uni) | E68: God Save the King | F68: Dieu protège le Roi | G68: anonyme | H68: anonyme | I68: vers 1745 | J68: vers 1745 | K68: — (usage coutumier depuis le XVIIIe s.) | L68: God save our gracious King! Long live our noble King! God save the King! Send him victorious, Happy and glorious, Long to reign over us, God save the King! | M68: — (écriture latine) | N68: Dieu protège notre gracieux Roi ! Longue vie à notre noble Roi ! Dieu protège le Roi ! Rends-le victorieux, Heureux et glorieux, Qu'il règne longtemps sur nous, Dieu protège le Roi ! | O68: Oui | P68: Domaine public (texte de vers 1745) ; vérification : https://fr.wikipedia.org/w/index.php?search=God+Save+the+King&title=Sp%C3%A9cial%3ARecherche&go=Go | Q68: https://commons.wikimedia.org/w/index.php?search=United+Kingdom+national+anthem&title=Special%3AMediaSearch&type=audio | R68: Territoire britannique d'outre-mer ; chant local « Hail to Bermuda » — utilise l'hymne de : Royaume-Uni | T68: BM
A69: Amérique du Nord | B69: 🇨🇦 | C69: Canada | D69: État souverain | E69: Ô Canada / O Canada | F69: Ô Canada | G69: Adolphe-Basile Routhier (fr.) ; Robert Stanley Weir (angl.) | H69: Calixa Lavallée | I69: 1880 (fr.), 1908 (angl.) | J69: 1880 | K69: 1980 | L69: Ô Canada ! Terre de nos aïeux, Ton front est ceint de fleurons glorieux ! Car ton bras sait porter l'épée, Il sait porter la croix ! Ton histoire est une épopée Des plus brillants exploits. Et ta valeur, de foi trempée, Protégera nos foyers et nos droits. Protégera nos foyers et nos droits. | M69: — (écriture latine) | N69: — (texte original en français) | O69: Oui | P69: Domaine public (texte de 1880 (fr.), 1908 (angl.)) ; vérification : https://fr.wikipedia.org/w/index.php?search=%C3%94+Canada&title=Sp%C3%A9cial%3ARecherche&go=Go | Q69: https://commons.wikimedia.org/w/index.php?search=Canada+national+anthem&title=Special%3AMediaSearch&type=audio | R69: Texte français d'origine reproduit ; la version anglaise officielle a été modifiée en 1980 et 2018 | T69: CA
A70: Amérique du Nord | B70: 🇨🇷 | C70: Costa Rica | D70: État souverain | E70: Himno Nacional de Costa Rica (Noble patria, tu hermosa bandera) | F70: Hymne national du Costa Rica | G70: José María Zeledón Brenes | H70: Manuel María Gutiérrez | I70: 1903 | J70: 1852 | K70: 1853 (paroles officielles 1949) | L70: Noble patria, tu hermosa bandera expresión de tu vida nos da; bajo el límpido azul de tu cielo blanca y pura descansa la paz. En la lucha tenaz de fecunda labor, que enrojece del hombre la faz, conquistaron tus hijos, labriegos sencillos, eterno prestigio, estima y honor, eterno prestigio, estima y honor. ¡Salve, oh tierra gentil! ¡Salve, oh madre de amor! Cuando alguno pretenda tu gloria manchar, verás a tu pueblo, valiente y viril, la tosca herramienta en arma trocar. ¡Salve, oh patria!, tu pródigo suelo dulce abrigo y sustento nos da; bajo el límpido azul de tu cielo, ¡vivan siempre el trabajo y la paz! | M70: — (écriture latine) | N70: Noble patrie, ton beau drapeau nous donne l'expression de ta vie ; sous le bleu limpide de ton ciel repose la paix, blanche et pure. Dans la lutte tenace d'un labeur fécond qui rougit le visage de l'homme, tes fils, simples paysans, ont conquis un prestige, une estime et un honneur éternels, un prestige, une estime et un honneur éternels. Salut, ô terre aimable ! Salut, ô mère d'amour ! Quand quelqu'un prétendra souiller ta gloire, tu verras ton peuple, vaillant et viril, changer son rude outil en arme. Salut, ô patrie ! Ton sol prodigue nous donne doux abri et subsistance ; sous le bleu limpide de ton ciel, vivent à jamais le travail et la paix ! | O70: Oui | P70: Domaine public (texte de 1903) ; vérification : https://fr.wikipedia.org/w/index.php?search=Noble+patria%2C+tu+hermosa+bandera&title=Sp%C3%A9cial%3ARecherche&go=Go | Q70: https://commons.wikimedia.org/w/index.php?search=Costa+Rica+national+anthem&title=Special%3AMediaSearch&type=audio | T70: CR
A71: Amérique du Nord | B71: 🇨🇺 | C71: Cuba | D71: État souverain | E71: La Bayamesa (Himno de Bayamo) | F71: L'Hymne de Bayamo | G71: Perucho Figueredo | H71: Perucho Figueredo | I71: 1868 | J71: 1867 | K71: 1940 | L71: Al combate, corred, bayameses, Que la patria os contempla orgullosa; No temáis una muerte gloriosa, Que morir por la patria es vivir. En cadenas vivir es vivir En afrenta y oprobio sumido; Del clarín escuchad el sonido; ¡A las armas, valientes, corred! | M71: — (écriture latine) | N71: Au combat, courez, gens de Bayamo, car la patrie vous contemple avec fierté ; ne craignez pas une mort glorieuse, car mourir pour la patrie, c'est vivre. Vivre enchaînés, c'est vivre plongés dans l'affront et l'opprobre ; écoutez le son du clairon ; aux armes, braves, courez ! | O71: Oui | P71: Domaine public (texte de 1868) ; vérification : https://fr.wikipedia.org/w/index.php?search=Himno+de+Bayamo&title=Sp%C3%A9cial%3ARecherche&go=Go | Q71: https://commons.wikimedia.org/w/index.php?search=Cuba+national+anthem&title=Special%3AMediaSearch&type=audio | T71: CU
A72: Amérique du Nord | B72: 🇨🇼 | C72: Curaçao | D72: Territoire / dépendance | E72: Himno di Kòrsou | F72: Hymne de Curaçao | G72: Guillermo Rosario, Mae Henriquez, Enrique Muller, Betty Doran | H72: Frater Candidus Nouwens, Errol Colina | I72: 1978 (révisé 2000) | J72: 1899 | K72: 1978 | L72: Non reproduites ici : texte postérieur à 1929, potentiellement protégé — voir la source. | O72: Non | P72: https://fr.wikipedia.org/w/index.php?search=Himno+di+K%C3%B2rsou&title=Sp%C3%A9cial%3ARecherche&go=Go | Q72: https://commons.wikimedia.org/w/index.php?search=Cura%C3%A7ao+national+anthem&title=Special%3AMediaSearch&type=audio | R72: Pays constitutif du Royaume des Pays-Bas (à vérifier) | T72: CW
A73: Amérique du Nord | B73: 🇩🇲 | C73: Dominique | D73: État souverain | E73: Isle of Beauty, Isle of Splendour | F73: Île de beauté, île de splendeur | G73: Wilfred Oscar Morgan Pond | H73: Lemuel McPherson Christian | I73: 1967 | J73: 1967 | K73: 1978 | L73: Non reproduites ici : texte postérieur à 1929, potentiellement protégé — voir la source. | O73: Non | P73: https://fr.wikipedia.org/w/index.php?search=Isle+of+Beauty%2C+Isle+of+Splendour&title=Sp%C3%A9cial%3ARecherche&go=Go | Q73: https://commons.wikimedia.org/w/index.php?search=Dominica+national+anthem&title=Special%3AMediaSearch&type=audio | T73: DM
A74: Amérique du Nord | B74: 🇺🇸 | C74: États-Unis | D74: État souverain | E74: The Star-Spangled Banner | F74: La Bannière étoilée | G74: Francis Scott Key | H74: John Stafford Smith | I74: 1814 | J74: vers 1773 | K74: 1931 | L74: O say can you see, by the dawn's early light, What so proudly we hailed at the twilight's last gleaming, Whose broad stripes and bright stars through the perilous fight, O'er the ramparts we watched, were so gallantly streaming? And the rocket's red glare, the bombs bursting in air, Gave proof through the night that our flag was still there; O say does that star-spangled banner yet wave O'er the land of the free and the home of the brave? | M74: — (écriture latine) | N74: Oh, dites, voyez-vous, aux premières lueurs de l'aube, ce que nous saluions si fièrement aux dernières lueurs du crépuscule, dont les larges bandes et les étoiles brillantes, pendant le périlleux combat, flottaient si vaillamment au-dessus des remparts que nous observions ? Et la lueur rouge des fusées, les bombes éclatant dans les airs prouvaient au cours de la nuit que notre drapeau était toujours là. Oh, dites, cette bannière étoilée flotte-t-elle encore sur la terre des hommes libres et la patrie des braves ? | O74: Oui | P74: Domaine public (texte de 1814) ; vérification : https://fr.wikipedia.org/w/index.php?search=The+Star-Spangled+Banner&title=Sp%C3%A9cial%3ARecherche&go=Go | Q74: https://commons.wikimedia.org/w/index.php?search=United+States+national+anthem&title=Special%3AMediaSearch&type=audio | R74: On chante la 1re strophe | T74: US
A75: Amérique du Nord | B75: 🇬🇩 | C75: Grenade | D75: État souverain | E75: Hail Grenada | F75: Salut, Grenade | G75: Irva Merle Baptiste-Blackett | H75: Louis Arnold Masanto | I75: 1974 | J75: 1974 | K75: 1974 | L75: Non reproduites ici : texte postérieur à 1929, potentiellement protégé — voir la source. | O75: Non | P75: https://fr.wikipedia.org/w/index.php?search=Hail+Grenada&title=Sp%C3%A9cial%3ARecherche&go=Go | Q75: https://commons.wikimedia.org/w/index.php?search=Grenada+national+anthem&title=Special%3AMediaSearch&type=audio | T75: GD
A76: Amérique du Nord | B76: 🇬🇱 | C76: Groenland | D76: Territoire / dépendance | E76: Nunarput utoqqarsuanngoravit | F76: Notre pays, toi qui es si vieux | G76: Henrik Lund | H76: Jonathan Petersen | I76: vers 1912 | J76: vers 1916 | K76: 1916 | L76: Non reproduites ici : version officielle révisée après 1929 ou texte non vérifié — voir la source. | O76: Non | P76: https://fr.wikipedia.org/w/index.php?search=Nunarput+utoqqarsuanngoravit&title=Sp%C3%A9cial%3ARecherche&go=Go | Q76: https://commons.wikimedia.org/w/index.php?search=Greenland+national+anthem&title=Special%3AMediaSearch&type=audio | R76: Territoire autonome danois ; second hymne officiel « Nuna asiilasooq » (1979) (à vérifier) | T76: GL
A77: Amérique du Nord | B77: 🇬🇵 | C77: Guadeloupe | D77: Territoire / dépendance (France) | E77: La Marseillaise | F77: La Marseillaise | G77: Claude Joseph Rouget de Lisle | H77: Claude Joseph Rouget de Lisle | I77: 1792 | J77: 1792 | K77: 1795 (définitivement 1879) | L77: Allons enfants de la Patrie, Le jour de gloire est arrivé ! Contre nous de la tyrannie L'étendard sanglant est levé, (bis) Entendez-vous dans les campagnes Mugir ces féroces soldats ? Ils viennent jusque dans vos bras Égorger vos fils, vos compagnes ! Aux armes, citoyens, Formez vos bataillons, Marchons, marchons ! Qu'un sang impur Abreuve nos sillons ! | M77: — (écriture latine) | N77: — (texte original en français) | O77: Oui | P77: Domaine public (texte de 1792) ; vérification : https://fr.wikipedia.org/w/index.php?search=La+Marseillaise&title=Sp%C3%A9cial%3ARecherche&go=Go | Q77: https://commons.wikimedia.org/w/index.php?search=France+national+anthem&title=Special%3AMediaSearch&type=audio | R77: Département et région d'outre-mer français — utilise l'hymne de : France | T77: GP
A78: Amérique du Nord | B78: 🇬🇹 | C78: Guatemala | D78: État souverain | E78: Himno Nacional de Guatemala (¡Guatemala feliz!) | F78: Hymne national du Guatemala | G78: José Joaquín Palma (révisé par José María Bonilla Ruano) | H78: Rafael Álvarez Ovalle | I78: 1896 (révisé 1934) | J78: 1896 | K78: 1896 | L78: Non reproduites ici : version officielle révisée après 1929 ou texte non vérifié — voir la source. | O78: Non | P78: https://fr.wikipedia.org/w/index.php?search=%C2%A1Guatemala+feliz%21&title=Sp%C3%A9cial%3ARecherche&go=Go | Q78: https://commons.wikimedia.org/w/index.php?search=Guatemala+national+anthem&title=Special%3AMediaSearch&type=audio | R78: Texte officiel actuel : version révisée de 1934 | T78: GT
A79: Amérique du Nord | B79: 🇭🇹 | C79: Haïti | D79: État souverain | E79: La Dessalinienne | F79: La Dessalinienne | G79: Justin Lhérisson | H79: Nicolas Geffrard | I79: 1903 | J79: 1903 | K79: 1904 | L79: Pour le Pays, pour la Patrie, Marchons unis, marchons unis. Dans nos rangs point de traîtres ! Du sol soyons seuls maîtres. Marchons unis, marchons unis Pour le Pays, pour la Patrie, Marchons, marchons, marchons unis, Pour le Pays, pour la Patrie. | M79: — (écriture latine) | N79: — (texte original en français ; il existe une version créole haïtienne) | O79: Oui | P79: Domaine public (texte de 1903) ; vérification : https://fr.wikipedia.org/w/index.php?search=La+Dessalinienne&title=Sp%C3%A9cial%3ARecherche&go=Go | Q79: https://commons.wikimedia.org/w/index.php?search=Haiti+national+anthem&title=Special%3AMediaSearch&type=audio | T79: HT
A80: Amérique du Nord | B80: 🇭🇳 | C80: Honduras | D80: État souverain | E80: Himno Nacional de Honduras | F80: Hymne national du Honduras | G80: Augusto Constancio Coello | H80: Carlos Hartling | I80: 1904 | J80: 1904 | K80: 1915 | L80: (Coro) Tu bandera, tu bandera es un lampo de cielo por un bloque, por un bloque de nieve cruzado; y se ven en su fondo sagrado cinco estrellas de pálido azul. En tu emblema, que un mar rumoroso con sus ondas bravías escuda, de un volcán, de un volcán tras la cima desnuda hay un astro, hay un astro de nítida luz. | M80: — (écriture latine) | N80: (Refrain) Ton drapeau, ton drapeau est un éclat de ciel traversé par un bloc, un bloc de neige ; et l'on voit sur son fond sacré cinq étoiles d'un bleu pâle. Sur ton emblème, qu'une mer bruissante protège de ses vagues farouches, derrière le sommet nu d'un volcan, d'un volcan, brille un astre, un astre d'une lumière nette. | O80: Oui | P80: Domaine public (texte de 1904) ; vérification : https://fr.wikipedia.org/w/index.php?search=Himno+Nacional+de+Honduras&title=Sp%C3%A9cial%3ARecherche&go=Go | Q80: https://commons.wikimedia.org/w/index.php?search=Honduras+national+anthem&title=Special%3AMediaSearch&type=audio | R80: On chante le refrain | T80: HN
A81: Amérique du Nord | B81: 🇰🇾 | C81: Îles Caïmans | D81: Territoire / dépendance (Royaume-Uni) | E81: God Save the King | F81: Dieu protège le Roi | G81: anonyme | H81: anonyme | I81: vers 1745 | J81: vers 1745 | K81: — (usage coutumier depuis le XVIIIe s.) | L81: God save our gracious King! Long live our noble King! God save the King! Send him victorious, Happy and glorious, Long to reign over us, God save the King! | M81: — (écriture latine) | N81: Dieu protège notre gracieux Roi ! Longue vie à notre noble Roi ! Dieu protège le Roi ! Rends-le victorieux, Heureux et glorieux, Qu'il règne longtemps sur nous, Dieu protège le Roi ! | O81: Oui | P81: Domaine public (texte de vers 1745) ; vérification : https://fr.wikipedia.org/w/index.php?search=God+Save+the+King&title=Sp%C3%A9cial%3ARecherche&go=Go | Q81: https://commons.wikimedia.org/w/index.php?search=United+Kingdom+national+anthem&title=Special%3AMediaSearch&type=audio | R81: Territoire britannique d'outre-mer ; chant local « Beloved Isle Cayman » — utilise l'hymne de : Royaume-Uni | T81: KY
A82: Amérique du Nord | B82: 🇺🇲 | C82: Îles mineures éloignées des États-Unis | D82: Territoire / dépendance (États-Unis) | E82: The Star-Spangled Banner | F82: La Bannière étoilée | G82: Francis Scott Key | H82: John Stafford Smith | I82: 1814 | J82: vers 1773 | K82: 1931 | L82: O say can you see, by the dawn's early light, What so proudly we hailed at the twilight's last gleaming, Whose broad stripes and bright stars through the perilous fight, O'er the ramparts we watched, were so gallantly streaming? And the rocket's red glare, the bombs bursting in air, Gave proof through the night that our flag was still there; O say does that star-spangled banner yet wave O'er the land of the free and the home of the brave? | M82: — (écriture latine) | N82: Oh, dites, voyez-vous, aux premières lueurs de l'aube, ce que nous saluions si fièrement aux dernières lueurs du crépuscule, dont les larges bandes et les étoiles brillantes, pendant le périlleux combat, flottaient si vaillamment au-dessus des remparts que nous observions ? Et la lueur rouge des fusées, les bombes éclatant dans les airs prouvaient au cours de la nuit que notre drapeau était toujours là. Oh, dites, cette bannière étoilée flotte-t-elle encore sur la terre des hommes libres et la patrie des braves ? | O82: Oui | P82: Domaine public (texte de 1814) ; vérification : https://fr.wikipedia.org/w/index.php?search=The+Star-Spangled+Banner&title=Sp%C3%A9cial%3ARecherche&go=Go | Q82: https://commons.wikimedia.org/w/index.php?search=United+States+national+anthem&title=Special%3AMediaSearch&type=audio | R82: Îles mineures éloignées des États-Unis (inhabitées) — utilise l'hymne de : États-Unis | T82: UM
A83: Amérique du Nord | B83: 🇹🇨 | C83: Îles Turques-et-Caïques | D83: Territoire / dépendance (Royaume-Uni) | E83: God Save the King | F83: Dieu protège le Roi | G83: anonyme | H83: anonyme | I83: vers 1745 | J83: vers 1745 | K83: — (usage coutumier depuis le XVIIIe s.) | L83: God save our gracious King! Long live our noble King! God save the King! Send him victorious, Happy and glorious, Long to reign over us, God save the King! | M83: — (écriture latine) | N83: Dieu protège notre gracieux Roi ! Longue vie à notre noble Roi ! Dieu protège le Roi ! Rends-le victorieux, Heureux et glorieux, Qu'il règne longtemps sur nous, Dieu protège le Roi ! | O83: Oui | P83: Domaine public (texte de vers 1745) ; vérification : https://fr.wikipedia.org/w/index.php?search=God+Save+the+King&title=Sp%C3%A9cial%3ARecherche&go=Go | Q83: https://commons.wikimedia.org/w/index.php?search=United+Kingdom+national+anthem&title=Special%3AMediaSearch&type=audio | R83: Territoire britannique d'outre-mer ; chant local « This Land of Ours » — utilise l'hymne de : Royaume-Uni | T83: TC
A84: Amérique du Nord | B84: 🇻🇬 | C84: Îles Vierges britanniques | D84: Territoire / dépendance (Royaume-Uni) | E84: God Save the King | F84: Dieu protège le Roi | G84: anonyme | H84: anonyme | I84: vers 1745 | J84: vers 1745 | K84: — (usage coutumier depuis le XVIIIe s.) | L84: God save our gracious King! Long live our noble King! God save the King! Send him victorious, Happy and glorious, Long to reign over us, God save the King! | M84: — (écriture latine) | N84: Dieu protège notre gracieux Roi ! Longue vie à notre noble Roi ! Dieu protège le Roi ! Rends-le victorieux, Heureux et glorieux, Qu'il règne longtemps sur nous, Dieu protège le Roi ! | O84: Oui | P84: Domaine public (texte de vers 1745) ; vérification : https://fr.wikipedia.org/w/index.php?search=God+Save+the+King&title=Sp%C3%A9cial%3ARecherche&go=Go | Q84: https://commons.wikimedia.org/w/index.php?search=United+Kingdom+national+anthem&title=Special%3AMediaSearch&type=audio | R84: Territoire britannique d'outre-mer ; chant local « Oh, Beautiful Virgin Islands » — utilise l'hymne de : Royaume-Uni | T84: VG
A85: Amérique du Nord | B85: 🇻🇮 | C85: Îles Vierges des États-Unis | D85: Territoire / dépendance | E85: Virgin Islands March | F85: Marche des îles Vierges | G85: Alton Augustus Adams | H85: Alton Augustus Adams | I85: 1919 | J85: 1919 | K85: 1963 | L85: Non reproduites ici : version officielle révisée après 1929 ou texte non vérifié — voir la source. | O85: Non | P85: https://fr.wikipedia.org/w/index.php?search=Virgin+Islands+March&title=Sp%C3%A9cial%3ARecherche&go=Go | Q85: https://commons.wikimedia.org/w/index.php?search=United+States+Virgin+Islands+national+anthem&title=Special%3AMediaSearch&type=audio | R85: Territoire des États-Unis (à vérifier) | T85: VI
A86: Amérique du Nord | B86: 🇯🇲 | C86: Jamaïque | D86: État souverain | E86: Jamaica, Land We Love | F86: Jamaïque, terre que nous aimons | G86: Hugh Braham Sherlock | H86: Robert Charles Lightbourne | I86: 1962 | J86: 1962 | K86: 1962 | L86: Non reproduites ici : texte postérieur à 1929, potentiellement protégé — voir la source. | O86: Non | P86: https://fr.wikipedia.org/w/index.php?search=Jamaica%2C+Land+We+Love&title=Sp%C3%A9cial%3ARecherche&go=Go | Q86: https://commons.wikimedia.org/w/index.php?search=Jamaica+national+anthem&title=Special%3AMediaSearch&type=audio | T86: JM
A87: Amérique du Nord | B87: 🇲🇶 | C87: Martinique | D87: Territoire / dépendance (France) | E87: La Marseillaise | F87: La Marseillaise | G87: Claude Joseph Rouget de Lisle | H87: Claude Joseph Rouget de Lisle | I87: 1792 | J87: 1792 | K87: 1795 (définitivement 1879) | L87: Allons enfants de la Patrie, Le jour de gloire est arrivé ! Contre nous de la tyrannie L'étendard sanglant est levé, (bis) Entendez-vous dans les campagnes Mugir ces féroces soldats ? Ils viennent jusque dans vos bras Égorger vos fils, vos compagnes ! Aux armes, citoyens, Formez vos bataillons, Marchons, marchons ! Qu'un sang impur Abreuve nos sillons ! | M87: — (écriture latine) | N87: — (texte original en français) | O87: Oui | P87: Domaine public (texte de 1792) ; vérification : https://fr.wikipedia.org/w/index.php?search=La+Marseillaise&title=Sp%C3%A9cial%3ARecherche&go=Go | Q87: https://commons.wikimedia.org/w/index.php?search=France+national+anthem&title=Special%3AMediaSearch&type=audio | R87: Collectivité territoriale française — utilise l'hymne de : France | T87: MQ
A88: Amérique du Nord | B88: 🇲🇽 | C88: Mexique | D88: État souverain | E88: Himno Nacional Mexicano | F88: Hymne national mexicain | G88: Francisco González Bocanegra | H88: Jaime Nunó | I88: 1853 | J88: 1854 | K88: 1943 | L88: (Coro) Mexicanos, al grito de guerra el acero aprestad y el bridón, y retiemble en sus centros la tierra al sonoro rugir del cañón. I Ciña ¡oh Patria! tus sienes de oliva de la paz el arcángel divino, que en el cielo tu eterno destino por el dedo de Dios se escribió. Mas si osare un extraño enemigo profanar con su planta tu suelo, piensa ¡oh Patria querida! que el cielo un soldado en cada hijo te dio. | M88: — (écriture latine) | N88: (Refrain) Mexicains, au cri de guerre, apprêtez l'acier et la bride, et que la terre tremble jusqu'en son centre au rugissement sonore du canon. I Que l'archange divin de la paix, ô Patrie, ceigne tes tempes d'olivier, car ton destin éternel a été écrit dans le ciel par le doigt de Dieu. Mais si un ennemi étranger osait profaner ton sol de son pied, songe, ô Patrie bien-aimée, que le ciel t'a donné un soldat en chacun de tes fils. | O88: Oui | P88: Domaine public (texte de 1853) ; vérification : https://fr.wikipedia.org/w/index.php?search=Himno+Nacional+Mexicano&title=Sp%C3%A9cial%3ARecherche&go=Go | Q88: https://commons.wikimedia.org/w/index.php?search=Mexico+national+anthem&title=Special%3AMediaSearch&type=audio | R88: La version officielle compte le refrain et 4 strophes ; refrain et 1re strophe reproduits | T88: MX
A89: Amérique du Nord | B89: 🇲🇸 | C89: Montserrat | D89: Territoire / dépendance (Royaume-Uni) | E89: God Save the King | F89: Dieu protège le Roi | G89: anonyme | H89: anonyme | I89: vers 1745 | J89: vers 1745 | K89: — (usage coutumier depuis le XVIIIe s.) | L89: God save our gracious King! Long live our noble King! God save the King! Send him victorious, Happy and glorious, Long to reign over us, God save the King! | M89: — (écriture latine) | N89: Dieu protège notre gracieux Roi ! Longue vie à notre noble Roi ! Dieu protège le Roi ! Rends-le victorieux, Heureux et glorieux, Qu'il règne longtemps sur nous, Dieu protège le Roi ! | O89: Oui | P89: Domaine public (texte de vers 1745) ; vérification : https://fr.wikipedia.org/w/index.php?search=God+Save+the+King&title=Sp%C3%A9cial%3ARecherche&go=Go | Q89: https://commons.wikimedia.org/w/index.php?search=United+Kingdom+national+anthem&title=Special%3AMediaSearch&type=audio | R89: Territoire britannique d'outre-mer — utilise l'hymne de : Royaume-Uni | T89: MS
A90: Amérique du Nord | B90: 🇳🇮 | C90: Nicaragua | D90: État souverain | E90: Salve a ti, Nicaragua | F90: Salut à toi, Nicaragua | G90: Salomón Ibarra Mayorga | H90: Luis Abraham Delgadillo (arr. d'une mélodie liturgique) | I90: 1939 | J90: XVIIIe s. | K90: 1939 (1971) | L90: Non reproduites ici : texte postérieur à 1929, potentiellement protégé — voir la source. | O90: Non | P90: https://fr.wikipedia.org/w/index.php?search=Salve+a+ti%2C+Nicaragua&title=Sp%C3%A9cial%3ARecherche&go=Go | Q90: https://commons.wikimedia.org/w/index.php?search=Nicaragua+national+anthem&title=Special%3AMediaSearch&type=audio | T90: NI
A91: Amérique du Nord | B91: 🇵🇦 | C91: Panama | D91: État souverain | E91: Himno Istmeño | F91: Hymne de l'Isthme | G91: Jerónimo de la Ossa | H91: Santos Jorge | I91: 1903 | J91: 1903 | K91: 1906 (1925) | L91: (Coro) Alcanzamos por fin la victoria en el campo feliz de la unión; con ardientes fulgores de gloria se ilumina la nueva nación. I Es preciso cubrir con un velo del pasado el calvario y la cruz; y que adorne el azul de tu cielo de concordia la espléndida luz. | M91: — (écriture latine) | N91: (Refrain) Nous avons enfin atteint la victoire sur le champ heureux de l'union ; d'ardentes lueurs de gloire illuminent la nouvelle nation. I Il faut couvrir d'un voile le calvaire et la croix du passé ; et que la splendide lumière de la concorde orne le bleu de ton ciel. | O91: Oui | P91: Domaine public (texte de 1903) ; vérification : https://fr.wikipedia.org/w/index.php?search=Himno+Istme%C3%B1o&title=Sp%C3%A9cial%3ARecherche&go=Go | Q91: https://commons.wikimedia.org/w/index.php?search=Panama+national+anthem&title=Special%3AMediaSearch&type=audio | T91: PA
A92: Amérique du Nord | B92: 🇧🇶 | C92: Pays-Bas caribéens | D92: Territoire / dépendance (Pays-Bas) | E92: Het Wilhelmus | F92: Le Guillaume | G92: attribué à Philippe de Marnix de Sainte-Aldegonde | H92: mélodie française anonyme (notée par Adrianus Valerius, 1626) | I92: 1568-1572 | J92: vers 1568 | K92: 1932 | L92: Wilhelmus van Nassouwe ben ik, van Duitsen bloed, den vaderland getrouwe blijf ik tot in den dood. Een Prinse van Oranje ben ik, vrij, onverveerd, den Koning van Hispanje heb ik altijd geëerd. Mijn schild ende betrouwen zijt Gij, o God mijn Heer, op U zo wil ik bouwen, verlaat mij nimmermeer. Dat ik doch vroom mag blijven, uw dienaar t'aller stond, de tirannie verdrijven die mij mijn hart doorwondt. | M92: — (écriture latine) | N92: Guillaume de Nassau je suis, de sang germanique, à la patrie fidèle je resterai jusqu'à la mort. Prince d'Orange je suis, libre et sans crainte, le Roi d'Espagne je l'ai toujours honoré. Mon bouclier et ma confiance, c'est Toi, ô Dieu mon Seigneur, c'est sur Toi que je veux bâtir, ne m'abandonne jamais. Que je demeure pieux, ton serviteur à toute heure, et chasse la tyrannie qui me blesse le cœur. | O92: Oui | P92: Domaine public (texte de 1568-1572) ; vérification : https://fr.wikipedia.org/w/index.php?search=Het+Wilhelmus&title=Sp%C3%A9cial%3ARecherche&go=Go | Q92: https://commons.wikimedia.org/w/index.php?search=Netherlands+national+anthem&title=Special%3AMediaSearch&type=audio | R92: Pays-Bas caribéens (Bonaire, Saint-Eustache, Saba) — utilise l'hymne de : Pays-Bas | T92: BQ
A93: Amérique du Nord | B93: 🇵🇷 | C93: Porto Rico | D93: Territoire / dépendance | E93: La Borinqueña | F93: La Borinqueña | G93: Manuel Fernández Juncos | H93: Félix Astol Artés | I93: 1903 | J93: 1867 | K93: 1952 (musique), 1977 (paroles) | L93: La tierra de Borinquen donde he nacido yo, es un jardín florido de mágico primor. Un cielo siempre nítido le sirve de dosel y dan arrullos plácidos las olas a sus pies. Cuando a sus playas llegó Colón, exclamó lleno de admiración: «¡Oh!, ¡oh!, ¡oh!, esta es la linda tierra que busco yo». Es Borinquen la hija, la hija del mar y el sol, del mar y el sol, del mar y el sol, del mar y el sol, del mar y el sol. | M93: — (écriture latine) | N93: La terre de Borinquen, où je suis né, est un jardin fleuri d'une beauté magique. Un ciel toujours limpide lui sert de dais, et les vagues bercent paisiblement ses pieds. Lorsque Colomb arriva sur ses plages, il s'exclama, plein d'admiration : « Oh ! oh ! oh ! voici la belle terre que je cherche. » Borinquen est la fille, la fille de la mer et du soleil, de la mer et du soleil, de la mer et du soleil, de la mer et du soleil, de la mer et du soleil. | O93: Oui | P93: Domaine public (texte de 1903) ; vérification : https://fr.wikipedia.org/w/index.php?search=La+Borinque%C3%B1a&title=Sp%C3%A9cial%3ARecherche&go=Go | Q93: https://commons.wikimedia.org/w/index.php?search=Puerto+Rico+national+anthem&title=Special%3AMediaSearch&type=audio | R93: Territoire non incorporé des États-Unis ; The Star-Spangled Banner est aussi joué | T93: PR
A94: Amérique du Nord | B94: 🇩🇴 | C94: République dominicaine | D94: État souverain | E94: Himno Nacional (Quisqueyanos valientes) | F94: Hymne national dominicain | G94: Emilio Prud'Homme | H94: José Reyes | I94: 1883 (révisé 1897) | J94: 1883 | K94: 1934 | L94: Quisqueyanos valientes, alcemos nuestro canto con viva emoción, y del mundo a la faz ostentemos nuestro invicto glorioso pendón. ¡Salve! el pueblo que intrépido y fuerte, a la guerra a morir se lanzó cuando en bélico reto de muerte sus cadenas de esclavo rompió. | M94: — (écriture latine) | N94: Vaillants Quisqueyanos, élevons notre chant avec une vive émotion, et, à la face du monde, arborons notre glorieux étendard invaincu. Salut au peuple qui, intrépide et fort, s'est lancé dans la guerre jusqu'à la mort lorsque, dans un défi guerrier à la mort, il brisa ses chaînes d'esclave. | O94: Oui | P94: Domaine public (texte de 1883 (révisé 1897)) ; vérification : https://fr.wikipedia.org/w/index.php?search=Quisqueyanos+valientes&title=Sp%C3%A9cial%3ARecherche&go=Go | Q94: https://commons.wikimedia.org/w/index.php?search=Dominican+Republic+national+anthem&title=Special%3AMediaSearch&type=audio | T94: DO
A95: Amérique du Nord | B95: 🇧🇱 | C95: Saint-Barthélemy | D95: Territoire / dépendance (France) | E95: La Marseillaise | F95: La Marseillaise | G95: Claude Joseph Rouget de Lisle | H95: Claude Joseph Rouget de Lisle | I95: 1792 | J95: 1792 | K95: 1795 (définitivement 1879) | L95: Allons enfants de la Patrie, Le jour de gloire est arrivé ! Contre nous de la tyrannie L'étendard sanglant est levé, (bis) Entendez-vous dans les campagnes Mugir ces féroces soldats ? Ils viennent jusque dans vos bras Égorger vos fils, vos compagnes ! Aux armes, citoyens, Formez vos bataillons, Marchons, marchons ! Qu'un sang impur Abreuve nos sillons ! | M95: — (écriture latine) | N95: — (texte original en français) | O95: Oui | P95: Domaine public (texte de 1792) ; vérification : https://fr.wikipedia.org/w/index.php?search=La+Marseillaise&title=Sp%C3%A9cial%3ARecherche&go=Go | Q95: https://commons.wikimedia.org/w/index.php?search=France+national+anthem&title=Special%3AMediaSearch&type=audio | R95: Collectivité d'outre-mer française — utilise l'hymne de : France | T95: BL
A96: Amérique du Nord | B96: 🇰🇳 | C96: Saint-Christophe-et-Niévès | D96: État souverain | E96: O Land of Beauty! | F96: Ô terre de beauté ! | G96: Kenrick Anderson Georges | H96: Kenrick Anderson Georges | I96: 1983 | J96: 1983 | K96: 1983 | L96: Non reproduites ici : texte postérieur à 1929, potentiellement protégé — voir la source. | O96: Non | P96: https://fr.wikipedia.org/w/index.php?search=O+Land+of+Beauty%21&title=Sp%C3%A9cial%3ARecherche&go=Go | Q96: https://commons.wikimedia.org/w/index.php?search=Saint+Kitts+and+Nevis+national+anthem&title=Special%3AMediaSearch&type=audio | T96: KN
A97: Amérique du Nord | B97: 🇸🇽 | C97: Saint-Martin | D97: Territoire / dépendance | E97: O Sweet Saint Martin's Land | F97: Ô douce terre de Saint-Martin | G97: Gérard Kemps | H97: Gérard Kemps | I97: 1958 | J97: 1958 | K97: — (usage officiel) | L97: Non reproduites ici : texte postérieur à 1929, potentiellement protégé — voir la source. | O97: Non | P97: https://fr.wikipedia.org/w/index.php?search=O+Sweet+Saint+Martin%27s+Land&title=Sp%C3%A9cial%3ARecherche&go=Go | Q97: https://commons.wikimedia.org/w/index.php?search=Sint+Maarten+national+anthem&title=Special%3AMediaSearch&type=audio | R97: Pays constitutif du Royaume des Pays-Bas (à vérifier) | T97: SX
A98: Amérique du Nord | B98: 🇲🇫 | C98: Saint-Martin | D98: Territoire / dépendance (France) | E98: La Marseillaise | F98: La Marseillaise | G98: Claude Joseph Rouget de Lisle | H98: Claude Joseph Rouget de Lisle | I98: 1792 | J98: 1792 | K98: 1795 (définitivement 1879) | L98: Allons enfants de la Patrie, Le jour de gloire est arrivé ! Contre nous de la tyrannie L'étendard sanglant est levé, (bis) Entendez-vous dans les campagnes Mugir ces féroces soldats ? Ils viennent jusque dans vos bras Égorger vos fils, vos compagnes ! Aux armes, citoyens, Formez vos bataillons, Marchons, marchons ! Qu'un sang impur Abreuve nos sillons ! | M98: — (écriture latine) | N98: — (texte original en français) | O98: Oui | P98: Domaine public (texte de 1792) ; vérification : https://fr.wikipedia.org/w/index.php?search=La+Marseillaise&title=Sp%C3%A9cial%3ARecherche&go=Go | Q98: https://commons.wikimedia.org/w/index.php?search=France+national+anthem&title=Special%3AMediaSearch&type=audio | R98: Collectivité d'outre-mer française — utilise l'hymne de : France | T98: MF
A99: Amérique du Nord | B99: 🇵🇲 | C99: Saint-Pierre-et-Miquelon | D99: Territoire / dépendance (France) | E99: La Marseillaise | F99: La Marseillaise | G99: Claude Joseph Rouget de Lisle | H99: Claude Joseph Rouget de Lisle | I99: 1792 | J99: 1792 | K99: 1795 (définitivement 1879) | L99: Allons enfants de la Patrie, Le jour de gloire est arrivé ! Contre nous de la tyrannie L'étendard sanglant est levé, (bis) Entendez-vous dans les campagnes Mugir ces féroces soldats ? Ils viennent jusque dans vos bras Égorger vos fils, vos compagnes ! Aux armes, citoyens, Formez vos bataillons, Marchons, marchons ! Qu'un sang impur Abreuve nos sillons ! | M99: — (écriture latine) | N99: — (texte original en français) | O99: Oui | P99: Domaine public (texte de 1792) ; vérification : https://fr.wikipedia.org/w/index.php?search=La+Marseillaise&title=Sp%C3%A9cial%3ARecherche&go=Go | Q99: https://commons.wikimedia.org/w/index.php?search=France+national+anthem&title=Special%3AMediaSearch&type=audio | R99: Collectivité d'outre-mer française — utilise l'hymne de : France | T99: PM
A100: Amérique du Nord | B100: 🇻🇨 | C100: Saint-Vincent-et-les-Grenadines | D100: État souverain | E100: Saint Vincent, Land So Beautiful | F100: Saint-Vincent, terre si belle | G100: Phyllis Joyce McClean Punnett | H100: Joel Bertram Miguel | I100: 1967 | J100: 1967 | K100: 1979 | L100: Non reproduites ici : texte postérieur à 1929, potentiellement protégé — voir la source. | O100: Non | P100: https://fr.wikipedia.org/w/index.php?search=Saint+Vincent%2C+Land+So+Beautiful&title=Sp%C3%A9cial%3ARecherche&go=Go | Q100: https://commons.wikimedia.org/w/index.php?search=Saint+Vincent+and+the+Grenadines+national+anthem&title=Special%3AMediaSearch&type=audio | T100: VC
...

Sheet Synthèse
A1: Continent | B1: Nombre de lignes | C1: dont États souverains | D1: Paroles reproduites | E1: Paroles non reproduites | F1: Hymnes sans paroles
A2: Afrique | B2: =COUNTIF(Hymnes!$A$2:$A$250,A2) -> 60 | C2: =COUNTIFS(Hymnes!$A$2:$A$250,A2,Hymnes!$D$2:$D$250,"État souverain") -> 54 | D2: =COUNTIFS(Hymnes!$A$2:$A$250,A2,Hymnes!$O$2:$O$250,"Oui") -> 8 | E2: =COUNTIFS(Hymnes!$A$2:$A$250,A2,Hymnes!$O$2:$O$250,"Non") -> 52 | F2: =COUNTIFS(Hymnes!$A$2:$A$250,A2,Hymnes!$O$2:$O$250,"Sans objet") -> 0
A3: Amérique du Nord | B3: =COUNTIF(Hymnes!$A$2:$A$250,A3) -> 42 | C3: =COUNTIFS(Hymnes!$A$2:$A$250,A3,Hymnes!$D$2:$D$250,"État souverain") -> 23 | D3: =COUNTIFS(Hymnes!$A$2:$A$250,A3,Hymnes!$O$2:$O$250,"Oui") -> 24 | E3: =COUNTIFS(Hymnes!$A$2:$A$250,A3,Hymnes!$O$2:$O$250,"Non") -> 18 | F3: =COUNTIFS(Hymnes!$A$2:$A$250,A3,Hymnes!$O$2:$O$250,"Sans objet") -> 0
A4: Amérique du Sud | B4: =COUNTIF(Hymnes!$A$2:$A$250,A4) -> 16 | C4: =COUNTIFS(Hymnes!$A$2:$A$250,A4,Hymnes!$D$2:$D$250,"État souverain") -> 12 | D4: =COUNTIFS(Hymnes!$A$2:$A$250,A4,Hymnes!$O$2:$O$250,"Oui") -> 14 | E4: =COUNTIFS(Hymnes!$A$2:$A$250,A4,Hymnes!$O$2:$O$250,"Non") -> 2 | F4: =COUNTIFS(Hymnes!$A$2:$A$250,A4,Hymnes!$O$2:$O$250,"Sans objet") -> 0
A5: Asie | B5: =COUNTIF(Hymnes!$A$2:$A$250,A5) -> 50 | C5: =COUNTIFS(Hymnes!$A$2:$A$250,A5,Hymnes!$D$2:$D$250,"État souverain") -> 46 | D5: =COUNTIFS(Hymnes!$A$2:$A$250,A5,Hymnes!$O$2:$O$250,"Oui") -> 11 | E5: =COUNTIFS(Hymnes!$A$2:$A$250,A5,Hymnes!$O$2:$O$250,"Non") -> 38 | F5: =COUNTIFS(Hymnes!$A$2:$A$250,A5,Hymnes!$O$2:$O$250,"Sans objet") -> 1
A6: Europe | B6: =COUNTIF(Hymnes!$A$2:$A$250,A6) -> 53 | C6: =COUNTIFS(Hymnes!$A$2:$A$250,A6,Hymnes!$D$2:$D$250,"État souverain") -> 45 | D6: =COUNTIFS(Hymnes!$A$2:$A$250,A6,Hymnes!$O$2:$O$250,"Oui") -> 38 | E6: =COUNTIFS(Hymnes!$A$2:$A$250,A6,Hymnes!$O$2:$O$250,"Non") -> 11 | F6: =COUNTIFS(Hymnes!$A$2:$A$250,A6,Hymnes!$O$2:$O$250,"Sans objet") -> 4
A7: Océanie | B7: =COUNTIF(Hymnes!$A$2:$A$250,A7) -> 28 | C7: =COUNTIFS(Hymnes!$A$2:$A$250,A7,Hymnes!$D$2:$D$250,"État souverain") -> 14 | D7: =COUNTIFS(Hymnes!$A$2:$A$250,A7,Hymnes!$O$2:$O$250,"Oui") -> 12 | E7: =COUNTIFS(Hymnes!$A$2:$A$250,A7,Hymnes!$O$2:$O$250,"Non") -> 16 | F7: =COUNTIFS(Hymnes!$A$2:$A$250,A7,Hymnes!$O$2:$O$250,"Sans objet") -> 0
A8: Total | B8: =SUM(B2:B7) -> 249 | C8: =SUM(C2:C7) -> 194 | D8: =SUM(D2:D7) -> 107 | E8: =SUM(E2:E7) -> 137 | F8: =SUM(F2:F7) -> 5

Sheet Notes
A1: Méthode et limites
A2: Périmètre | B2: 249 pays et territoires (référentiel mledoze/countries) ; l'Antarctique est exclu : il ne relève d'aucune souveraineté, seulement de revendications gelées par le traité sur l'Antarctique. Les territoires sans hymne propre reprennent l'hymne de l'État de rattachement (voir colonne Remarques).
A3: Continents | B3: Rattachement continental du référentiel ; les pays transcontinentaux (Russie, Turquie, Kazakhstan…) sont classés selon le premier continent indiqué. Les îles subantarctiques suivent la classification M49 de l'ONU : Terres australes françaises en Afrique, îles Heard-et-MacDonald en Océanie, île Bouvet et Géorgie du Sud en Amérique du Sud.
A4: Drapeau | B4: Emoji drapeau Unicode. S'affiche en couleur sur Mac, mobile et la plupart des navigateurs ; Excel sous Windows peut n'afficher que les deux lettres du code pays.
A5: Paroles | B5: Texte intégral reproduit uniquement pour les paroles écrites avant 1929 (domaine public), dans la version officiellement chantée. Pour les autres, la colonne « Source des paroles » renvoie vers Wikipédia.
A6: Translittération | B6: Fournie pour les écritures non latines (grec, cyrillique, arménien, japonais, coréen, chinois, devanagari, bengali, hébreu, arabe).
A7: Traductions | B7: Traductions françaises de travail, établies pour ce tableau ; à relire avant toute publication. Quand une version française officielle existe (Belgique, Suisse, Canada, Haïti), elle est indiquée.
A8: Audio | B8: Les fichiers ne pouvaient pas être téléchargés depuis l'environnement de travail : chaque lien ouvre la recherche audio de Wikimedia Commons (enregistrements libres, souvent .ogg ou .mp3) pour l'hymne concerné.
A9: Audio direct | B9: Colonne « Fichier audio direct » : collez-y l'URL d'un fichier .mp3 ou .ogg (par ex. un lien upload.wikimedia.org). Le site Planète Hymnes affiche alors un lecteur intégré dans la fiche.
A10: Code ISO | B10: Code ISO 3166-1 alpha-2 utilisé par le site pour placer chaque ligne sur la carte. À ne pas modifier.
A11: Fiabilité | B11: Données établies à partir des connaissances disponibles à mi-2026 ; les mentions « à vérifier » signalent les informations les moins sûres. Les hymnes changent parfois (ex. Nigeria 2024, Niger 2023).
